[{"model": "blog.comment", "pk": 1, "fields": {"creator": 1, "content": "What a great post!", "content_type": 7, "object_id": 1, "created_at": "2023-09-17T19:33:50.726Z", "modified_at": "2023-09-17T19:33:50.752Z"}}, {"model": "blog.comment", "pk": 2, "fields": {"creator": 1, "content": "I like myself!", "content_type": 4, "object_id": 1, "created_at": "2023-09-17T19:33:50.726Z", "modified_at": "2023-09-17T19:33:50.752Z"}}, {"model": "blog.comment", "pk": 3, "fields": {"creator": 1, "content": "Ah bah, on attend patiemment le contenu du coup !", "content_type": 7, "object_id": 2, "created_at": "2023-09-24T20:58:46.693Z", "modified_at": "2023-09-24T20:58:46.693Z"}}, {"model": "blog.tag", "pk": 1, "fields": {"value": "django"}}, {"model": "blog.tag", "pk": 2, "fields": {"value": "example"}}, {"model": "blog.post", "pk": 1, "fields": {"author": 1, "created_at": "2023-09-16T18:55:11.718Z", "modified_at": "2023-09-19T21:42:34.264Z", "published_at": "2023-09-19T21:42:26Z", "title": "An example post", "slug": "an-example-post", "summary": "A short example of a post.", "content": "<h3> An example post </h3>\r\n<p> This is an example post, that uses HTML to render itself. </p>", "tags": [1, 2]}}, {"model": "blog.post", "pk": 2, "fields": {"author": 1, "created_at": "2023-09-19T21:33:44.615Z", "modified_at": "2023-09-19T21:42:39.966Z", "published_at": "2023-09-19T21:42:37Z", "title": "Advanced Django : A Review", "slug": "advanced-django-a-review", "summary": "This great course is a must-do for anyone looking to take the next Django step.", "content": "Content à remplir.", "tags": [1]}}, {"model": "blog.post", "pk": 3, "fields": {"author": 2, "created_at": "2023-09-21T01:26:11.021Z", "modified_at": "2023-09-21T01:26:11.021Z", "published_at": "2023-09-21T01:25:20Z", "title": "Django vs Python", "slug": "django-vs-python", "summary": "The duel of two mastodontes", "content": "Are they really in concurrence though ? Let me know your thoughts.", "tags": [1]}}, {"model": "blango_auth.User", "pk": 1, "fields": {"password": "pbkdf2_sha256$260000$km9rcM9HkrAd9lOFzm18Ao$zMXu+6ezQiJy2BrEqscC9ZExZVfY8jY96frtPIyiepE=", "last_login": "2023-09-21T22:02:19.707Z", "is_superuser": true, "username": "codio", "first_name": "Boualem", "last_name": "Mansour", "email": "codio@example.com", "is_staff": true, "is_active": true, "date_joined": "2023-09-16T18:49:09Z", "groups": [], "user_permissions": []}}, {"model": "blango_auth.User", "pk": 2, "fields": {"password": "pbkdf2_sha256$260000$XuFBFY0AxNAazZmRP8cgMi$MIPJ2V0DOOiukZeF8dM+4n0C0c5a1OpRQXMfL1ER2tY=", "last_login": null, "is_superuser": false, "username": "akrame", "first_name": "", "last_name": "", "email": "", "is_staff": false, "is_active": true, "date_joined": "2023-09-19T21:34:00.670Z", "groups": [], "user_permissions": []}}]